<?xml version="1.0" encoding="utf-8" ?>
<LanguageData>
    <MsgTouchAnimalJoin>{0}La caresse douce fait {1}un choix bien élevé de rejoindre{2}.</MsgTouchAnimalJoin>
    <MsgAddictionTouchAnimal>{0}Laissez-vous tenter par des caresses {1}, {0}S’il n’y a pas de soin de longuement toucher{1}, La réaction de retrait va commencer</MsgAddictionTouchAnimal>
    <TitleAnimalsWantToTouch>Choisissez un animal qui veut être touché</TitleAnimalsWantToTouch>
    <TitleAssumedSkillLevel>Supposons le niveau de compétence du formateur</TitleAssumedSkillLevel>
    <TitleTouchBehaviorInformation>Toucher le message de comportement</TitleTouchBehaviorInformation>
    <LabelAnimalKind>Type d'animal</LabelAnimalKind>
    <LabelAnimalSkillRequire>Classement de l'animal avicole requis</LabelAnimalSkillRequire>
    <LabelChanceToJoin>Probabilité d'adhésion</LabelChanceToJoin>
    <LabelWillTouch>Palpable et de les toucher</LabelWillTouch>
    <LabelWontTouch>Je ne peux pas le toucher</LabelWontTouch>
</LanguageData>